LICENSE
README.md
setup.py
mathexp.egg-info/PKG-INFO
mathexp.egg-info/SOURCES.txt
mathexp.egg-info/dependency_links.txt
mathexp.egg-info/requires.txt
mathexp.egg-info/top_level.txt
maths/__init__.py