Metadata-Version: 2.1
Name: mathexp
Version: 0.0.2
Summary: Mathematical Experiments
Home-page: https://github.com/JWKennington/mathexp
Author: J. W. Kennington
Author-email: jameswkennington@gmail.com
Project-URL: Bug Reports, https://github.com/JWKennington/mathexp/issues
Project-URL: Funding, https://www.buymeacoffee.com/locallytrivial
Project-URL: Source, https://github.com/JWKennington/mathexp
Project-URL: Documentation, https://mathexp.readthedocs.io/en/latest/
Keywords: symbolic math,combinatorics,finite groups
Classifier: Development Status :: 3 - Alpha
Classifier: License :: OSI Approved :: MIT License
Classifier: Programming Language :: Python :: 3
Classifier: Programming Language :: Python :: 3.7
Classifier: Programming Language :: Python :: 3.8
Classifier: Programming Language :: Python :: 3.9
Classifier: Programming Language :: Python :: 3.10
Classifier: Programming Language :: Python :: 3 :: Only
Requires-Python: >=3.7, <4
License-File: LICENSE
Requires-Dist: sympy
Provides-Extra: dev
Requires-Dist: check-manifest; extra == "dev"
Provides-Extra: test
Requires-Dist: pytest; extra == "test"
Requires-Dist: pytest-cov; extra == "test"
